Metadata-Version: 2.1
Name: cookiedb
Version: 9.0.0
Summary: CookieDB is a noSQL document database.
Home-page: https://github.com/jaedsonpys/cookiedb
Author: Jaedson Silva
Author-email: jaedson.dev@proton.me
License: Apache License
Project-URL: License, https://github.com/jaedsonpys/cookiedb/blob/master/LICENSE
Project-URL: Documentation, https://jaedsonpys.github.io/cookiedb/
Keywords: database,noSQL,document,db,engine
Classifier: License :: OSI Approved :: Apache Software License
Classifier: Development Status :: 5 - Production/Stable
Classifier: Intended Audience :: Developers
Classifier: Intended Audience :: System Administrators
Classifier: Intended Audience :: Science/Research
Classifier: Natural Language :: English
Classifier: Operating System :: OS Independent
Classifier: Programming Language :: Python :: 3
Classifier: Topic :: Database :: Database Engines/Servers
License-File: LICENSE
